LICENCE.txt
MANIFEST.in
README.rst
setup.py
django_urls_map/__init__.py
django_urls_map/models.py
django_urls_map.egg-info/PKG-INFO
django_urls_map.egg-info/SOURCES.txt
django_urls_map.egg-info/dependency_links.txt
django_urls_map.egg-info/not-zip-safe
django_urls_map.egg-info/top_level.txt
django_urls_map/management/__init__.py
django_urls_map/management/commands/__init__.py
django_urls_map/management/commands/urlmap.py