Metadata-Version: 1.0
Name: django-urls-map
Version: 0.1
Summary: 
